{
  "project_info": {
    "project_number": "1067571485803",
    "project_id": "polo-debug",
    "storage_bucket": "polo-debug.appspot.com"
  },
  "client": [
    {
      "client_info": {
        "mobilesdk_app_id": "1:1067571485803:android:4021ed2859a398048c252e",
        "android_client_info": {
          "package_name": "com.polo.warehouse.debug"
        }
      },
      "oauth_client": [
        {
          "client_id": "1067571485803-t4aj3lfmdn21llkr5ujhl766hp5i4sni.apps.googleusercontent.com",
          "client_type": 1,
          "android_info": {
            "package_name": "com.polo.warehouse.debug",
            "certificate_hash": "ff093d65c5ce0a022f76b9e0a042098b77febd9b"
          }
        },
        {
          "client_id": "1067571485803-aod4l4fo8dfje1af01v6qurmnesa06t9.apps.googleusercontent.com",
          "client_type": 3
        }
      ],
      "api_key": [
        {
          "current_key": "AIzaSyBUfit6wX5_tcz5ayb82eOSP0cDZiRRVWM"
        }
      ],
      "services": {
        "appinvite_service": {
          "other_platform_oauth_client": [
            {
              "client_id": "1067571485803-aod4l4fo8dfje1af01v6qurmnesa06t9.apps.googleusercontent.com",
              "client_type": 3
            }
          ]
        }
      }
    }
  ],
  "configuration_version": "1"
}